MANIFEST.in
README.md
setup.py
pylinapp/__init__.py
pylinapp/functions.py
pylinapp/main.py
pylinapp/variables.py
pylinapp.egg-info/PKG-INFO
pylinapp.egg-info/SOURCES.txt
pylinapp.egg-info/dependency_links.txt
pylinapp.egg-info/entry_points.txt
pylinapp.egg-info/requires.txt
pylinapp.egg-info/top_level.txt